opentelemetry/util/genai/version.py
opentelemetry/util/genai/langsmith/__init__.py
opentelemetry/util/genai/processor/__init__.py
opentelemetry/util/genai/processor/content_normalizer.py
opentelemetry/util/genai/processor/langsmith_span_processor.py
opentelemetry/util/genai/processor/message_reconstructor.py
opentelemetry_util_genai_langsmith_translator.pth
splunk_otel_util_genai_translator_langsmith-0.1.0.dist-info/METADATA
splunk_otel_util_genai_translator_langsmith-0.1.0.dist-info/WHEEL
splunk_otel_util_genai_translator_langsmith-0.1.0.dist-info/licenses/LICENSE
splunk_otel_util_genai_translator_langsmith-0.1.0.dist-info/RECORD
