Metadata-Version: 2.4
Name: splunk-otel-util-genai-translator-langsmith
Version: 0.1.0
Summary: Langsmith -> GenAI translator emitter for OpenTelemetry GenAI
Project-URL: Homepage, https://github.com/open-telemetry/opentelemetry-python-contrib
Project-URL: Repository, https://github.com/open-telemetry/opentelemetry-python-contrib
License-Expression: Apache-2.0
License-File: LICENSE
Classifier: Development Status :: 4 - Beta
Classifier: Intended Audience :: Developers
Classifier: License :: OSI Approved :: Apache Software License
Classifier: Programming Language :: Python
Classifier: Programming Language :: Python :: 3
Classifier: Programming Language :: Python :: 3.9
Classifier: Programming Language :: Python :: 3.10
Classifier: Programming Language :: Python :: 3.11
Classifier: Programming Language :: Python :: 3.12
Classifier: Programming Language :: Python :: 3.13
Requires-Python: >=3.9
Requires-Dist: opentelemetry-api>=1.31.0
Requires-Dist: opentelemetry-instrumentation~=0.52b1
Requires-Dist: opentelemetry-sdk>=1.31.0
Requires-Dist: opentelemetry-semantic-conventions~=0.52b1
Requires-Dist: splunk-otel-util-genai>=0.1.4
Provides-Extra: test
Requires-Dist: pytest>=7.0.0; extra == 'test'
